odoo8_addon_payment_redsys-8.0.1.0.2.99.dev29-py2.7-nspkg.pth
odoo8_addon_payment_redsys-8.0.1.0.2.99.dev29.dist-info/DESCRIPTION.rst
odoo8_addon_payment_redsys-8.0.1.0.2.99.dev29.dist-info/METADATA
odoo8_addon_payment_redsys-8.0.1.0.2.99.dev29.dist-info/RECORD
odoo8_addon_payment_redsys-8.0.1.0.2.99.dev29.dist-info/WHEEL
odoo8_addon_payment_redsys-8.0.1.0.2.99.dev29.dist-info/metadata.json
odoo8_addon_payment_redsys-8.0.1.0.2.99.dev29.dist-info/namespace_packages.txt
odoo8_addon_payment_redsys-8.0.1.0.2.99.dev29.dist-info/top_level.txt
odoo_addons/payment_redsys/README.rst
odoo_addons/payment_redsys/__init__.py
odoo_addons/payment_redsys/__openerp__.py
odoo_addons/payment_redsys/controllers/__init__.py
odoo_addons/payment_redsys/controllers/main.py
odoo_addons/payment_redsys/i18n/bg.po
odoo_addons/payment_redsys/i18n/ca.po
odoo_addons/payment_redsys/i18n/es.po
odoo_addons/payment_redsys/i18n/eu.po
odoo_addons/payment_redsys/i18n/fr.po
odoo_addons/payment_redsys/i18n/gl.po
odoo_addons/payment_redsys/i18n/hr.po
odoo_addons/payment_redsys/i18n/nl.po
odoo_addons/payment_redsys/i18n/payment_redsys.pot
odoo_addons/payment_redsys/i18n/pt.po
odoo_addons/payment_redsys/i18n/pt_BR.po
odoo_addons/payment_redsys/i18n/ru.po
odoo_addons/payment_redsys/i18n/sl.po
odoo_addons/payment_redsys/i18n/tr.po
odoo_addons/payment_redsys/models/__init__.py
odoo_addons/payment_redsys/models/redsys.py
odoo_addons/payment_redsys/static/description/icon.png
odoo_addons/payment_redsys/static/src/img/redsys_icon.png
odoo_addons/payment_redsys/views/payment_acquirer.xml
odoo_addons/payment_redsys/views/redsys.xml
